{
	"DescriptionsForMultiplicators": [
		{
			"Key": "P/E",
			"Value": "Показывает, сколько лет должна проработать компания, получая ту же прибыль, чтобы окупить акционерный капитал."
		},
		{
			"Key": "P/S",
			"Value": "Показывает, сколько вы платите за 1 рубль выручки компании."
		},
		{
			"Key": "P/B",
			"Value": "Показывает, сколько денег можно выручить за компанию, если продать все ее имущество."
		},
		{
			"Key": "P/BV",
			"Value": "Позволяет оценить, переплачивает ли инвестор за остаток, который ему достанется, если компания обанкротится."
		},
		{
			"Key": "D/E",
			"Value": "Показывает, сколько заёмных средств приходится на каждый рубль собственного капитала."
		},
		{
			"Key": "EV/EBIDA",
			"Value": "Показывает, сколько прибылей до уплаты процентов, налогов и амортизации должна заработать компания, чтобы окупить реальную рыночную цену компании."
		},
		{
			"Key": "DEBT/EBIDA",
			"Value": "Сообщает о достаточности или нехватке ресурсов для погашения займов и процентных ставок по ним."
		},
		{
			"Key": "ROE",
			"Value": "Показывает, как компания генерирует чистую прибыль за счёт собственных средств, по которым компания не выплачивает проценты."
		},
		{
			"Key": "ROA",
			"Value": "Показывает, как компания использует все активы, в том числе и заёмные, для получения прибыли."
		}
	]
}